anduinbridge/__init__.py
anduinbridge/anduinbridge.py
AnduinBridge-1.2.1.dist-info/LICENSE.md
AnduinBridge-1.2.1.dist-info/METADATA
AnduinBridge-1.2.1.dist-info/WHEEL
AnduinBridge-1.2.1.dist-info/top_level.txt
AnduinBridge-1.2.1.dist-info/zip-safe
AnduinBridge-1.2.1.dist-info/RECORD
