Metadata-Version: 2.1
Name: AnduinBridge
Version: 1.2.1
Summary: Wraps injected Anduin DB routines in REST API.
Home-page: https://apage224@bitbucket.org/samteccmd/anduinbridge.git
Maintainer: Adam Page
Maintainer-email: adam.page@samtec.com
License: BSD
Platform: UNKNOWN
Classifier: Development Status :: 5 - Production/Stable
Classifier: Intended Audience :: Developers
Classifier: License :: OSI Approved :: MIT License
Classifier: Natural Language :: English
Classifier: Operating System :: OS Independent
Classifier: Programming Language :: Python :: 2.7
Classifier: Programming Language :: Python :: 3.7
Classifier: Programming Language :: Python :: Implementation :: PyPy
Classifier: Topic :: Communications
Classifier: Topic :: Internet
Classifier: Topic :: Software Development :: Libraries
Classifier: Topic :: Software Development :: Libraries :: Python Modules
Classifier: Topic :: System :: Networking
Requires-Dist: future
Provides-Extra: libev
Requires-Dist: pyev ; extra == 'libev'
